serializers/__init__.py
serializers/factory_serializer.py
serializers/dict_serializer/__init__.py
serializers/dict_serializer/functions.py
serializers/json/__init__.py
serializers/json/json.py
serializers/json/parse_json.py
serializers/xml/__init__.py
serializers/xml/const.py
serializers/xml/funcs.py
serializers/xml/xml.py
serializers/xml/xml_parser.py
jsonigigovno-2.0.dist-info/METADATA
jsonigigovno-2.0.dist-info/WHEEL
jsonigigovno-2.0.dist-info/top_level.txt
jsonigigovno-2.0.dist-info/RECORD
